thoth/__init__.py
thoth/__main__.py
thoth/cli.py
thoth/indexer.py
thoth/server.py
thoth/cli/__init__.py
thoth/cli/main.py
thoth/config/__init__.py
thoth/config/settings.py
thoth/development_memory/__init__.py
thoth/development_memory/session_hooks.py
thoth/development_memory/tracker.py
thoth/embeddings/__init__.py
thoth/embeddings/base.py
thoth/embeddings/remote_embedder.py
thoth/embeddings/tfidf.py
thoth/mcp/__init__.py
thoth/mcp/server.py
thoth/parser/__init__.py
thoth/parser/api_detector.py
thoth/parser/call_analyzer.py
thoth/parser/import_resolver.py
thoth/parser/python_parser.py
thoth/storage/__init__.py
thoth/storage/backend.py
thoth/storage/database.py
thoth/storage/models.py
thoth/visualizations/__init__.py
thoth/visualizations/mermaid.py
mcp_server_thoth-0.4.0.dist-info/METADATA
mcp_server_thoth-0.4.0.dist-info/WHEEL
mcp_server_thoth-0.4.0.dist-info/entry_points.txt
mcp_server_thoth-0.4.0.dist-info/licenses/LICENSE
mcp_server_thoth-0.4.0.dist-info/RECORD
