Metadata-Version: 2.4
Name: mcp-server-thoth
Version: 0.4.0
Summary: MCP server for persistent codebase memory with semantic search and development tracking
Project-URL: Homepage, https://github.com/braininahat/thoth
Project-URL: Bug Tracker, https://github.com/braininahat/thoth/issues
Project-URL: Source Code, https://github.com/braininahat/thoth
Author-email: Varun Shijo <varunshi@buffalo.edu>
Maintainer-email: Varun Shijo <varun.shijo@gmail.com>
License: MIT
License-File: LICENSE
Keywords: analysis,codebase,mcp,memory,semantic-search,visualization
Classifier: Development Status :: 4 - Beta
Classifier: Intended Audience :: Developers
Classifier: License :: OSI Approved :: MIT License
Classifier: Programming Language :: Python :: 3
Classifier: Programming Language :: Python :: 3.10
Classifier: Programming Language :: Python :: 3.11
Classifier: Programming Language :: Python :: 3.12
Requires-Python: <3.13,>=3.10
Requires-Dist: aiosqlite>=0.20.0
Requires-Dist: chromadb>=0.4.0
Requires-Dist: click>=8.1.0
Requires-Dist: fastapi>=0.100.0
Requires-Dist: httpx>=0.24.0
Requires-Dist: mcp>=1.1.0
Requires-Dist: networkx>=3.0
Requires-Dist: numpy>=1.24.0
Requires-Dist: pytz>=2025.2
Requires-Dist: pyyaml>=6.0
Requires-Dist: rich>=13.0.0
Requires-Dist: scikit-learn>=1.3.0
Requires-Dist: sqlalchemy>=2.0.0
Requires-Dist: torch>=2.0.0
Requires-Dist: transformers>=4.30.0
Requires-Dist: tzlocal>=5.3.1
Requires-Dist: uvicorn>=0.30.0
Requires-Dist: vllm>=0.8.5
Provides-Extra: cache
Requires-Dist: redis>=5.0.0; extra == 'cache'
Provides-Extra: dashboard
Requires-Dist: gradio>=5.0.0; extra == 'dashboard'
Requires-Dist: plotly>=5.0.0; extra == 'dashboard'
Provides-Extra: dev
Requires-Dist: mypy>=1.10.0; extra == 'dev'
Requires-Dist: pytest-asyncio>=0.23.0; extra == 'dev'
Requires-Dist: pytest>=8.0.0; extra == 'dev'
Requires-Dist: ruff>=0.4.0; extra == 'dev'
